siem/__init__.py
siem/cmaq.py
siem/emiss.py
siem/point.py
siem/proxy.py
siem/siem.py
siem/spatial.py
siem/temporal.py
siem/user.py
siem/wrfchemi.py
siem-0.0.1.dist-info/licenses/LICENSE
tests/__init__.py
tests/test_PointSources.py
tests/test_PointSources_total_emiss.py
tests/test_add_cmaq_emission_attrs.py
tests/test_assign_factor_simulation_days.py
tests/test_calculate_centroid.py
tests/test_calculate_density_map.py
tests/test_calculate_emission.py
tests/test_calculate_julian.py
tests/test_calculate_sum_points.py
tests/test_convert_str_to_julian.py
tests/test_create_cmaq_file_name.py
tests/test_create_date_limits.py
tests/test_create_date_s19.py
tests/test_create_emiss_point.py
tests/test_create_global_attrs.py
tests/test_create_gpd_from_point_src.py
tests/test_create_hour_matrix.py
tests/test_create_tflag_matrix.py
tests/test_create_tflag_variable.py
tests/test_create_wrf_grid.py
tests/test_get_highway_query.py
tests/test_group_sources.py
tests/test_group_sources_wrfchemi.py
tests/test_ktn_year_to_fluxes.py
tests/test_point_emiss_to_xarray.py
tests/test_prepare_netcdf_cmaq.py
tests/test_prepare_wrfchemi_netcdf.py
tests/test_read_point_sources.py
tests/test_read_spatial_proxy.py
tests/test_report_emission.py
tests/test_retrieve_proj_from_geo.py
tests/test_spatial_emission.py
tests/test_spatiotemporal_emission.py
tests/test_speciate_all.py
tests/test_speciate_emission.py
tests/test_speciate_wrfchemi.py
tests/test_split_by_weekday.py
tests/test_to_25hr_profile.py
tests/test_total_emission.py
tests/test_transform_cmaq_units_points.py
tests/test_transform_weekprofile_df.py
tests/test_transform_wrfchemi_units.py
tests/test_transform_wrfchemi_units_point.py
tests/test_wrfchemi_pm_sum.py
siem-0.0.1.dist-info/METADATA
siem-0.0.1.dist-info/WHEEL
siem-0.0.1.dist-info/top_level.txt
siem-0.0.1.dist-info/RECORD
