Metadata-Version: 2.4
Name: siem
Version: 0.0.1
Summary: A package to build WRF-Chem and CMAQ emission files
Author: Mario Gavidia-Calderón
Author-email: mario.calderon@iag.usp.br
License: MIT
Classifier: License :: OSI Approved :: MIT License
Classifier: Programming Language :: Python :: 3.10
Classifier: Operating System :: OS Independent
Requires-Python: >=3.10
License-File: LICENSE
Requires-Dist: xarray
Requires-Dist: pyproj
Requires-Dist: osmnx
Requires-Dist: pseudonetcdf
Requires-Dist: geopandas
Provides-Extra: dev
Requires-Dist: pytest; extra == "dev"
Requires-Dist: twine; extra == "dev"
Dynamic: author
Dynamic: author-email
Dynamic: classifier
Dynamic: description
Dynamic: description-content-type
Dynamic: license
Dynamic: license-file
Dynamic: provides-extra
Dynamic: requires-dist
Dynamic: requires-python
Dynamic: summary
